LICENSE
nowcastlib/__init__.py
nowcastlib/cli/__init__.py
nowcastlib/cli/triangulate.py
nowcastlib/datasets.py
nowcastlib/dynlag.py
nowcastlib/gis.py
nowcastlib/pipeline/README.md
nowcastlib/pipeline/__init__.py
nowcastlib/pipeline/cli.py
nowcastlib/pipeline/features/__init__.py
nowcastlib/pipeline/features/generate.py
nowcastlib/pipeline/process/__init__.py
nowcastlib/pipeline/process/postprocess/__init__.py
nowcastlib/pipeline/process/postprocess/cli.py
nowcastlib/pipeline/process/preprocess/__init__.py
nowcastlib/pipeline/process/preprocess/cli.py
nowcastlib/pipeline/process/utils.py
nowcastlib/pipeline/split/__init__.py
nowcastlib/pipeline/split/cli.py
nowcastlib/pipeline/standardize/__init__.py
nowcastlib/pipeline/structs/__init__.py
nowcastlib/pipeline/structs/config.py
nowcastlib/pipeline/sync/__init__.py
nowcastlib/pipeline/sync/cli.py
nowcastlib/pipeline/utils.py
nowcastlib/signals.py
nowcastlib/utils.py
nowcastlib-3.1.0.dist-info/entry_points.txt
nowcastlib-3.1.0.dist-info/LICENSE
nowcastlib-3.1.0.dist-info/WHEEL
nowcastlib-3.1.0.dist-info/METADATA
nowcastlib-3.1.0.dist-info/RECORD
