Metadata-Version: 2.1
Name: nowcastlib
Version: 3.1.0
Summary: 🧙🔧 Utils that can be reused and shared across and beyond the ESO Nowcast project
Home-page: https://giuliostarace.com/nowcastlib/
License: GPL-3.0-only
Keywords: nowcast,turbulence,forecasting,data-science,time series
Author: Giulio Starace
Author-email: giulio.starace@gmail.com
Requires-Python: >=3.7.1,<4.0
Classifier: License :: OSI Approved :: GNU General Public License v3 (GPLv3)
Classifier: Programming Language :: Python :: 3
Classifier: Programming Language :: Python :: 3.8
Classifier: Programming Language :: Python :: 3.9
Requires-Dist: ConfigArgParse (>=1.4.1,<2.0.0)
Requires-Dist: attrs (>=21.2.0,<22.0.0)
Requires-Dist: cattrs (>=1.7.1,<2.0.0)
Requires-Dist: importlib-metadata (>=4.6.3,<5.0.0)
Requires-Dist: matplotlib (>=3.4.2,<4.0.0)
Requires-Dist: numpy (>=1.19.2,<1.20.0)
Requires-Dist: pandas (>=1.2.4,<2.0.0)
Requires-Dist: scikit-learn (>=0.24.2,<0.25.0)
Requires-Dist: skyfield (>=1.39,<2.0)
Project-URL: Repository, https://github.com/thesofakillers/nowcastlib
